python_tunnelclient-1.1.0.dist-info/DESCRIPTION.rst
python_tunnelclient-1.1.0.dist-info/METADATA
python_tunnelclient-1.1.0.dist-info/RECORD
python_tunnelclient-1.1.0.dist-info/WHEEL
python_tunnelclient-1.1.0.dist-info/entry_points.txt
python_tunnelclient-1.1.0.dist-info/metadata.json
python_tunnelclient-1.1.0.dist-info/top_level.txt
tunnelclient/__init__.py
tunnelclient/version.py
tunnelclient/api/__init__.py
tunnelclient/api/constants.py
tunnelclient/api/exceptions.py
tunnelclient/api/v2/__init__.py
tunnelclient/api/v2/tunnel.py
tunnelclient/hacking/__init__.py
tunnelclient/hacking/checks.py
tunnelclient/osc/__init__.py
tunnelclient/osc/plugin.py
tunnelclient/osc/v2/__init__.py
tunnelclient/osc/v2/amphora.py
tunnelclient/osc/v2/availabilityzone.py
tunnelclient/osc/v2/availabilityzoneprofile.py
tunnelclient/osc/v2/certificate.py
tunnelclient/osc/v2/constants.py
tunnelclient/osc/v2/flavor.py
tunnelclient/osc/v2/flavorprofile.py
tunnelclient/osc/v2/health_monitor.py
tunnelclient/osc/v2/l7policy.py
tunnelclient/osc/v2/l7rule.py
tunnelclient/osc/v2/listener.py
tunnelclient/osc/v2/member.py
tunnelclient/osc/v2/pool.py
tunnelclient/osc/v2/provider.py
tunnelclient/osc/v2/quota.py
tunnelclient/osc/v2/resource.py
tunnelclient/osc/v2/secgroup.py
tunnelclient/osc/v2/user.py
tunnelclient/osc/v2/utils.py
tunnelclient/osc/v2/validate.py
tunnelclient/osc/v2/vpn_server.py
tunnelclient/tests/__init__.py
tunnelclient/tests/fakes.py
tunnelclient/tests/functional/__init__.py
tunnelclient/tests/functional/base.py
tunnelclient/tests/functional/osc/__init__.py
tunnelclient/tests/functional/osc/v2/__init__.py
tunnelclient/tests/unit/__init__.py
tunnelclient/tests/unit/test_hacking.py
tunnelclient/tests/unit/api/__init__.py
tunnelclient/tests/unit/api/test_tunnel.py
tunnelclient/tests/unit/osc/__init__.py
tunnelclient/tests/unit/osc/v2/__init__.py
tunnelclient/tests/unit/osc/v2/constants.py
tunnelclient/tests/unit/osc/v2/fakes.py
tunnelclient/tests/unit/osc/v2/test_amphora.py
tunnelclient/tests/unit/osc/v2/test_availabilityzone.py
tunnelclient/tests/unit/osc/v2/test_availabilityzoneprofile.py
tunnelclient/tests/unit/osc/v2/test_flavor.py
tunnelclient/tests/unit/osc/v2/test_flavorprofile.py
tunnelclient/tests/unit/osc/v2/test_health_monitor.py
